pandorasat/__init__.py
pandorasat/data/benchmark.csv
pandorasat/data/pandora.mplstyle
pandorasat/detectormixins.py
pandorasat/hardware.py
pandorasat/irdetector.py
pandorasat/orbit.py
pandorasat/phoenix.py
pandorasat/plotting.py
pandorasat/utils.py
pandorasat/visibledetector.py
pandorasat-0.12.6.dist-info/LICENSE
pandorasat-0.12.6.dist-info/METADATA
pandorasat-0.12.6.dist-info/WHEEL
pandorasat-0.12.6.dist-info/RECORD
