Metadata-Version: 2.3
Name: pandorasat
Version: 0.12.6
Summary: 
Author: Christina Hedges
Author-email: christina.l.hedges@nasa.gov
Requires-Python: >=3.9,<3.13
Classifier: Programming Language :: Python :: 3
Classifier: Programming Language :: Python :: 3.9
Classifier: Programming Language :: Python :: 3.10
Classifier: Programming Language :: Python :: 3.11
Classifier: Programming Language :: Python :: 3.12
Requires-Dist: appdirs (>=1.4.4,<2.0.0)
Requires-Dist: astropy (>=5.3.3)
Requires-Dist: astroquery (>=0.4.6)
Requires-Dist: matplotlib (>=3.8.0)
Requires-Dist: numpy (>=1.26.0)
Requires-Dist: openpyxl (>=3.1.5,<4.0.0)
Requires-Dist: pandas[tabulate] (>=2.2.3,<3.0.0)
Requires-Dist: pandoraref (>=0.1.5)
Requires-Dist: pyarrow (<20.0.0)
Requires-Dist: rich (>=13.0.0)
Requires-Dist: scipy (>=1.11.2)
Requires-Dist: stsynphot (>=1.3.0)
Requires-Dist: synphot (>=1.3.0)
Requires-Dist: tabulate (>=0.9.0,<0.10.0)
Requires-Dist: tqdm (>=4.60.1)
